tasks_runner/__init__.py
tasks_runner/_task.py
tasks_runner/_tasks_runner.py
tasks_runner/_utils/__init__.py
tasks_runner/_utils/_chainable.py
tasks_runner-0.1.4.dist-info/LICENSE.txt
tasks_runner-0.1.4.dist-info/METADATA
tasks_runner-0.1.4.dist-info/WHEEL
tasks_runner-0.1.4.dist-info/RECORD
