Metadata-Version: 2.1
Name: tasks-runner
Version: 0.1.4
Summary: A simple concurrent tasks runner with progress bar
Home-page: https://github.com/sebastianguerra/tasks-runner
License: MIT
Keywords: tasks,jobs,concurrent,progress,bar,runner
Author: Sebastian Guerra
Author-email: spguerraespinoza@gmail.com
Requires-Python: >=3.12,<4.0
Classifier: License :: OSI Approved :: MIT License
Classifier: Programming Language :: Python :: 3
Classifier: Programming Language :: Python :: 3.12
Requires-Dist: loguru (>=0.7.2,<0.8.0)
Requires-Dist: tqdm (>=4.66.5,<5.0.0)
Project-URL: Repository, https://github.com/sebastianguerra/tasks-runner
